iab_mapper/__init__.py
iab_mapper/cli.py
iab_mapper/embeddings.py
iab_mapper/io_utils.py
iab_mapper/llm.py
iab_mapper/matching.py
iab_mapper/normalize.py
iab_mapper/pipeline.py
iab_mapper/updater.py
iab_mapper/data/iab_2x.json
iab_mapper/data/iab_3x.json
iab_mapper/data/synonyms_2x.json
iab_mapper/data/synonyms_3x.json
iab_mapper/data/vectors_channel.json
iab_mapper/data/vectors_environment.json
iab_mapper/data/vectors_format.json
iab_mapper/data/vectors_language.json
iab_mapper/data/vectors_source.json
iab_mapper/data/vectors_type.json
iab_mapper-1.0.0.dist-info/licenses/LICENSE
iab_mapper-1.0.0.dist-info/METADATA
iab_mapper-1.0.0.dist-info/WHEEL
iab_mapper-1.0.0.dist-info/entry_points.txt
iab_mapper-1.0.0.dist-info/top_level.txt
iab_mapper-1.0.0.dist-info/RECORD
