Metadata-Version: 2.4
Name: iab-mapper
Version: 1.0.0
Summary: Local IAB Content Taxonomy 2.x -> 3.0 mapper with vectors, SCD, OpenRTB/VAST exporters.
Author: Mixpeek
License: BSD-2-Clause
Project-URL: Homepage, https://github.com/mixpeek/iab-mapper
Project-URL: Repository, https://github.com/mixpeek/iab-mapper
Project-URL: Issues, https://github.com/mixpeek/iab-mapper/issues
Keywords: iab,taxonomy,content,openrtb,ctv,classification
Classifier: License :: OSI Approved :: BSD License
Classifier: Programming Language :: Python :: 3
Classifier: Programming Language :: Python :: 3 :: Only
Classifier: Programming Language :: Python :: 3.9
Classifier: Programming Language :: Python :: 3.10
Classifier: Programming Language :: Python :: 3.11
Classifier: Programming Language :: Python :: 3.12
Classifier: Operating System :: OS Independent
Classifier: Intended Audience :: Developers
Classifier: Topic :: Software Development :: Libraries
Requires-Python: >=3.9
License-File: LICENSE
Requires-Dist: pandas>=2.1
Requires-Dist: rapidfuzz>=3.0
Requires-Dist: typer>=0.12
Requires-Dist: rich>=13.7
Requires-Dist: numpy>=1.26
Requires-Dist: orjson>=3.10
Requires-Dist: tqdm>=4.66
Requires-Dist: scikit-learn>=1.4
Requires-Dist: requests>=2.31
Provides-Extra: emb
Requires-Dist: sentence-transformers>=3.0; extra == "emb"
Dynamic: license-file
